odoo/addons/invoice_product_name_description/README.rst
odoo/addons/invoice_product_name_description/__init__.py
odoo/addons/invoice_product_name_description/__manifest__.py
odoo/addons/invoice_product_name_description/models/__init__.py
odoo/addons/invoice_product_name_description/models/account_invoice_line.py
odoo/addons/invoice_product_name_description/static/description/icon.png
odoo12_addon_invoice_product_name_description-12.0.1.0.0.dist-info/METADATA
odoo12_addon_invoice_product_name_description-12.0.1.0.0.dist-info/WHEEL
odoo12_addon_invoice_product_name_description-12.0.1.0.0.dist-info/top_level.txt
odoo12_addon_invoice_product_name_description-12.0.1.0.0.dist-info/RECORD
