Metadata-Version: 2.1
Name: odoo12-addon-invoice_product_name_description
Version: 12.0.1.0.0
Summary: Only code, name and attributes in product description.
Home-page: https://www.sygel.es
Author: Sygel
Classifier: Programming Language :: Python
Classifier: Framework :: Odoo
Classifier: Framework :: Odoo :: 12.0
Requires-Python: >=3.5
Requires-Dist: odoo<12.1dev,>=12.0a
